{
  "config": {
    "v_rhe_grid": [
      -0.7,
      -0.6,
      -0.5,
      -0.4,
      -0.3,
      -0.2,
      -0.1,
      0.0,
      0.05,
      0.1,
      0.2,
      0.3,
      0.4,
      0.5,
      0.6,
      0.7,
      0.8,
      0.9,
      1.0
    ],
    "mesh_ny": 200,
    "formulation": "logc_muh",
    "initializer": "debye_boltzmann",
    "counterion_mode": "steric (bikerman)",
    "stern_capacitance_f_m2": 0.1,
    "exponent_clip": 100.0,
    "subfunction_labels": [
      "u_O2",
      "u_H2O2",
      "mu_H",
      "phi"
    ]
  },
  "rows": [
    {
      "V_RHE": -0.7,
      "method": "warm<--23.353",
      "z_factor_ss": 1.0,
      "ic_fallback": true,
      "ic_fallback_reason": "picard_max_iters_delta=2",
      "ic_picard_iters": 50,
      "z_at_build": [
        0.0,
        0.0,
        1.0
      ],
      "boltzmann_z_at_build": 1.0,
      "F_norm_total": 4.936285395403147e+21,
      "F_norms_per_block": [
        112163086142.89406,
        2.2075739399127116e+21,
        4.4151478802740764e+21,
        0.006196085244224698
      ],
      "ic_norm_per_block": [
        0.0,
        391.7373340769127,
        992.8560019211952,
        928.5956695296919
      ],
      "ss_norm_per_block": [
        22.903969125085354,
        539.1824269450116,
        763.4497583995129,
        537.5434496687317
      ],
      "abs_diff_per_block": [
        22.903969125085354,
        188.78911968383974,
        556.0872257683842,
        626.8744904880372
      ],
      "rel_diff_per_block": [
        1.0,
        0.35013960071642575,
        0.7283874539880122,
        1.1661838515088536
      ],
      "inf_diff_per_block": [
        0.6989141639762091,
        24.38630434135179,
        19.187176555877684,
        22.064144945434364
      ]
    },
    {
      "V_RHE": -0.6,
      "method": "warm<--19.461",
      "z_factor_ss": 1.0,
      "ic_fallback": true,
      "ic_fallback_reason": "picard_max_iters_delta=2",
      "ic_picard_iters": 50,
      "z_at_build": [
        0.0,
        0.0,
        1.0
      ],
      "boltzmann_z_at_build": 1.0,
      "F_norm_total": 4.936285395403137e+21,
      "F_norms_per_block": [
        112163086142.89395,
        2.2075739399127074e+21,
        4.4151478802740675e+21,
        0.006147483452954072
      ],
      "ic_norm_per_block": [
        0.0,
        391.7373340769127,
        860.2456821067574,
        795.9391453111645
      ],
      "ss_norm_per_block": [
        22.755234109267544,
        539.1811377494024,
        682.3583353190127,
        456.7962140737371
      ],
      "abs_diff_per_block": [
        22.755234109267544,
        188.78544426144873,
        468.0148700297356,
        533.547415379521
      ],
      "rel_diff_per_block": [
        1.0,
        0.3501336212343381,
        0.6858784392381339,
        1.1680206598502907
      ],
      "inf_diff_per_block": [
        0.6941491756139048,
        24.382657082592104,
        15.8280879143636,
        18.557227346235013
      ]
    },
    {
      "V_RHE": -0.5,
      "method": "warm<--15.569",
      "z_factor_ss": 1.0,
      "ic_fallback": true,
      "ic_fallback_reason": "picard_max_iters_delta=2",
      "ic_picard_iters": 50,
      "z_at_build": [
        0.0,
        0.0,
        1.0
      ],
      "boltzmann_z_at_build": 1.0,
      "F_norm_total": 4.936285395403147e+21,
      "F_norms_per_block": [
        112163086142.89395,
        2.2075739399127116e+21,
        4.4151478802740764e+21,
        0.006079522431520783
      ],
      "ic_norm_per_block": [
        0.0,
        391.7373340769127,
        727.6522063810303,
        663.2826210926372
      ],
      "ss_norm_per_block": [
        22.596287202964604,
        539.1798283035824,
        603.3647473959426,
        378.03025790879235
      ],
      "abs_diff_per_block": [
        22.596287202964604,
        188.78165644455328,
        380.4754709227188,
        438.54678279457806
      ],
      "rel_diff_per_block": [
        1.0,
        0.35012744641897237,
        0.6305894942732568,
        1.1600838123925694
      ],
      "inf_diff_per_block": [
        0.6890575598172801,
        24.37887246028852,
        13.245419683037642,
        15.049254828598393
      ]
    },
    {
      "V_RHE": -0.4,
      "method": "warm<--11.677",
      "z_factor_ss": 1.0,
      "ic_fallback": true,
      "ic_fallback_reason": "picard_max_iters_delta=2",
      "ic_picard_iters": 50,
      "z_at_build": [
        0.0,
        0.0,
        1.0
      ],
      "boltzmann_z_at_build": 1.0,
      "F_norm_total": 4.936285395403166e+21,
      "F_norms_per_block": [
        112163086142.89395,
        2.2075739399127203e+21,
        4.4151478802740937e+21,
        0.005977942783432046
      ],
      "ic_norm_per_block": [
        0.0,
        391.7373340769127,
        595.0868341297128,
        530.6260968741097
      ],
      "ss_norm_per_block": [
        22.422715661934397,
        539.1785035995996,
        527.0329719468967,
        301.9002690042215
      ],
      "abs_diff_per_block": [
        22.422715661934397,
        188.77773818896142,
        295.26945157940025,
        341.6479670816477
      ],
      "rel_diff_per_block": [
        1.0,
        0.3501210395604904,
        0.5602485371809931,
        1.1316583725099973
      ],
      "inf_diff_per_block": [
        0.6834995351200082,
        24.37492036470576,
        13.253057831084824,
        11.55213974810621
      ]
    },
    {
      "V_RHE": -0.3,
      "method": "warm<--7.784",
      "z_factor_ss": 1.0,
      "ic_fallback": true,
      "ic_fallback_reason": "picard_max_iters_delta=2",
      "ic_picard_iters": 50,
      "z_at_build": [
        0.0,
        0.0,
        1.0
      ],
      "boltzmann_z_at_build": 1.0,
      "F_norm_total": 4.936285395403147e+21,
      "F_norms_per_block": [
        112163086142.89372,
        2.2075739399127116e+21,
        4.4151478802740764e+21,
        0.005810069844470839
      ],
      "ic_norm_per_block": [
        0.0,
        391.7373340769127,
        462.5737278460034,
        397.9695726555822
      ],
      "ss_norm_per_block": [
        22.225690599994632,
        539.1771964573139,
        454.206537025619,
        229.65006894994696
      ],
      "abs_diff_per_block": [
        22.225690599994632,
        188.77370167882003,
        217.34023103202514,
        242.58857220496142
      ],
      "rel_diff_per_block": [
        1.0,
        0.35011440194274807,
        0.47850529068842157,
        1.0563400799928977
      ],
      "inf_diff_per_block": [
        0.6771993005378447,
        24.37078595299422,
        13.262408517872785,
        8.085940788970635
      ]
    },
    {
      "V_RHE": -0.2,
      "method": "warm<--3.892",
      "z_factor_ss": 1.0,
      "ic_fallback": true,
      "ic_fallback_reason": "picard_max_iters_delta=2",
      "ic_picard_iters": 50,
      "z_at_build": [
        0.0,
        0.0,
        1.0
      ],
      "boltzmann_z_at_build": 1.0,
      "F_norm_total": 4.936285395403157e+21,
      "F_norms_per_block": [
        112163086142.89401,
        2.207573939912716e+21,
        4.415147880274085e+21,
        0.005482014184719821
      ],
      "ic_norm_per_block": [
        0.0,
        391.7373340769127,
        330.17582296051637,
        265.3130484370549
      ],
      "ss_norm_per_block": [
        21.98318082694052,
        539.1761241277402,
        386.1435323058741,
        164.00174939656378
      ],
      "abs_diff_per_block": [
        21.98318082694052,
        188.76986426734177,
        161.40930262849804,
        141.28167018901468
      ],
      "rel_diff_per_block": [
        1.0,
        0.3501079810845239,
        0.4180033824848363,
        0.8614644094276647
      ],
      "inf_diff_per_block": [
        0.6694826157161863,
        24.366691747604747,
        13.276000475701327,
        4.6997461360402015
      ]
    },
    {
      "V_RHE": -0.1,
      "method": "warm<-+0.000",
      "z_factor_ss": 1.0,
      "ic_fallback": true,
      "ic_fallback_reason": "picard_max_iters_delta=2",
      "ic_picard_iters": 50,
      "z_at_build": [
        0.0,
        0.0,
        1.0
      ],
      "boltzmann_z_at_build": 1.0,
      "F_norm_total": 4.936285395403147e+21,
      "F_norms_per_block": [
        112163086142.89368,
        2.2075739399127116e+21,
        4.4151478802740764e+21,
        0.004598967570488003
      ],
      "ic_norm_per_block": [
        0.0,
        391.7373340769127,
        198.1242066922704,
        132.65652421852744
      ],
      "ss_norm_per_block": [
        21.628052590757427,
        539.1770920983416,
        324.47382458855367,
        111.14795036079035
      ],
      "abs_diff_per_block": [
        21.628052590757427,
        188.769666674392,
        157.83303230028844,
        42.16115120334716
      ],
      "rel_diff_per_block": [
        1.0,
        0.35010698607344004,
        0.48642762632834036,
        0.37932459452909845
      ],
      "inf_diff_per_block": [
        0.6583549100319416,
        24.365524426085315,
        13.304883044978343,
        1.5519745783797012
      ]
    },
    {
      "V_RHE": 0.0,
      "method": "warm<-+1.946",
      "z_factor_ss": 1.0,
      "ic_fallback": true,
      "ic_fallback_reason": "picard_max_iters_delta=2",
      "ic_picard_iters": 50,
      "z_at_build": [
        0.0,
        0.0,
        1.0
      ],
      "boltzmann_z_at_build": 1.0,
      "F_norm_total": 4.936285395403147e+21,
      "F_norms_per_block": [
        112163086142.89365,
        2.2075739399127116e+21,
        4.4151478802740764e+21,
        9.745442406136581e-20
      ],
      "ic_norm_per_block": [
        0.0,
        391.7373340769127,
        68.45316152458004,
        0.0
      ],
      "ss_norm_per_block": [
        20.986417218720952,
        539.1933948636697,
        270.683182598963,
        80.39918649398479
      ],
      "abs_diff_per_block": [
        20.986417218720952,
        188.80191323267277,
        211.71371293107347,
        80.39918649398479
      ],
      "rel_diff_per_block": [
        1.0,
        0.3501562056048733,
        0.7821457945717406,
        1.0
      ],
      "inf_diff_per_block": [
        0.6399033176657706,
        24.39403031724415,
        13.40235583385662,
        3.304793949840336
      ]
    },
    {
      "V_RHE": 0.05,
      "method": "warm<-+3.892",
      "z_factor_ss": 1.0,
      "ic_fallback": true,
      "ic_fallback_reason": "picard_max_iters_delta=2",
      "ic_picard_iters": 50,
      "z_at_build": [
        0.0,
        0.0,
        1.0
      ],
      "boltzmann_z_at_build": 1.0,
      "F_norm_total": 4.936285395403147e+21,
      "F_norms_per_block": [
        112163086142.90297,
        2.2075739399127116e+21,
        4.4151478802740764e+21,
        0.011958716633804682
      ],
      "ic_norm_per_block": [
        0.0,
        391.7373340769127,
        24.504436509542337,
        66.32826210926372
      ],
      "ss_norm_per_block": [
        20.50288822589776,
        539.2210020176524,
        247.43699823470084,
        73.93944517362571
      ],
      "abs_diff_per_block": [
        20.50288822589776,
        188.86383400667617,
        251.18693932204386,
        134.52887074482194
      ],
      "rel_diff_per_block": [
        1.0,
        0.3502531119893089,
        1.015155134899374,
        1.819446581306084
      ],
      "inf_diff_per_block": [
        0.6313126651809183,
        24.45541630047792,
        13.523852814076228,
        4.871964550652355
      ]
    },
    {
      "V_RHE": 0.1,
      "method": "warm<-+7.784",
      "z_factor_ss": 1.0,
      "ic_fallback": true,
      "ic_fallback_reason": "picard_max_iters_delta=2",
      "ic_picard_iters": 50,
      "z_at_build": [
        0.0,
        0.0,
        1.0
      ],
      "boltzmann_z_at_build": 1.0,
      "F_norm_total": 4.936285395403147e+21,
      "F_norms_per_block": [
        112163086143.01411,
        2.2075739399127116e+21,
        4.4151478802740764e+21,
        0.06316944857984395
      ],
      "ic_norm_per_block": [
        0.0,
        391.7373340769127,
        72.89702465437473,
        132.65652421852744
      ],
      "ss_norm_per_block": [
        19.945197366690483,
        539.2711582091425,
        227.14984608004252,
        71.30351518230344
      ],
      "abs_diff_per_block": [
        19.945197366690483,
        188.98725610711773,
        295.78326284908906,
        190.80293589248654
      ],
      "rel_diff_per_block": [
        1.0,
        0.35044940421943327,
        1.3021503996303023,
        2.67592608028729
      ],
      "inf_diff_per_block": [
        0.6388387063153376,
        24.591347441401147,
        13.723511646225194,
        6.481166008222074
      ]
    },
    {
      "V_RHE": 0.2,
      "method": "warm<-+11.677",
      "z_factor_ss": 1.0,
      "ic_fallback": true,
      "ic_fallback_reason": "picard_max_iters_delta=1.221e-05",
      "ic_picard_iters": 50,
      "z_at_build": [
        0.0,
        0.0,
        1.0
      ],
      "boltzmann_z_at_build": 1.0,
      "F_norm_total": 4.936285395403147e+21,
      "F_norms_per_block": [
        112163086145.10434,
        2.2075739399127116e+21,
        4.4151478802740764e+21,
        0.6938376702141731
      ],
      "ic_norm_per_block": [
        0.0,
        391.7373340769127,
        202.8241206555382,
        265.3130484370549
      ],
      "ss_norm_per_block": [
        18.765029775379496,
        539.4289701898597,
        191.64099209487006,
        69.66020291573712
      ],
      "abs_diff_per_block": [
        18.765029775379496,
        189.45614062651126,
        392.24929175377315,
        306.4255116947388
      ],
      "rel_diff_per_block": [
        1.0,
        0.351216102761091,
        2.046792220526566,
        4.398860452149407
      ],
      "inf_diff_per_block": [
        0.8424394342051791,
        25.227735672175733,
        14.304831890663216,
        9.773016149879576
      ]
    },
    {
      "V_RHE": 0.3,
      "method": "warm<-+15.569",
      "z_factor_ss": 1.0,
      "ic_fallback": false,
      "ic_fallback_reason": null,
      "ic_picard_iters": 21,
      "z_at_build": [
        0.0,
        0.0,
        1.0
      ],
      "boltzmann_z_at_build": 1.0,
      "F_norm_total": 26873.810620510863,
      "F_norms_per_block": [
        546.2021380891794,
        12015.850840306406,
        24031.701751538978,
        0.003943057615037381
      ],
      "ic_norm_per_block": [
        32.99459194048843,
        398.7652632233202,
        80.969609867267,
        85.06888261419057
      ],
      "ss_norm_per_block": [
        15.201111853705399,
        539.5203588835049,
        134.2371908799289,
        63.237649097298615
      ],
      "abs_diff_per_block": [
        27.2536041633094,
        171.68276978667149,
        65.93435231681103,
        43.40716586842498
      ],
      "rel_diff_per_block": [
        1.7928691286266738,
        0.31821370029845686,
        0.49117798044349203,
        0.6864133390164128
      ],
      "inf_diff_per_block": [
        4.200279921421747,
        20.88586090196852,
        2.1341446588801922,
        5.036423425184562
      ]
    },
    {
      "V_RHE": 0.4,
      "method": "warm<-+19.461",
      "z_factor_ss": 1.0,
      "ic_fallback": false,
      "ic_fallback_reason": null,
      "ic_picard_iters": 21,
      "z_at_build": [
        0.0,
        0.0,
        1.0
      ],
      "boltzmann_z_at_build": 1.0,
      "F_norm_total": 3066.079780080706,
      "F_norms_per_block": [
        3066.0758877242884,
        0.25819586781820664,
        4.8787126338123,
        0.005779024275814389
      ],
      "ic_norm_per_block": [
        58.439231764201594,
        405.9683593877634,
        97.41053476341332,
        109.56172596562728
      ],
      "ss_norm_per_block": [
        13.190728964212806,
        539.1915644306408,
        72.64708987250107,
        66.22955141448267
      ],
      "abs_diff_per_block": [
        45.38964630434548,
        160.61596087787328,
        45.474198018423486,
        46.838206702031556
      ],
      "rel_diff_per_block": [
        3.4410263775027268,
        0.29788292598285665,
        0.625960352964348,
        0.7072100852519025
      ],
      "inf_diff_per_block": [
        7.412821017890078,
        18.41609408160884,
        7.411431840361864,
        7.4612012557813205
      ]
    },
    {
      "V_RHE": 0.5,
      "method": "warm<-+23.353",
      "z_factor_ss": 1.0,
      "ic_fallback": false,
      "ic_fallback_reason": null,
      "ic_picard_iters": 21,
      "z_at_build": [
        0.0,
        0.0,
        1.0
      ],
      "boltzmann_z_at_build": 1.0,
      "F_norm_total": 1105.9110377012134,
      "F_norms_per_block": [
        1105.9054794384188,
        0.0931288824645905,
        3.505016959836237,
        0.006370099671833941
      ],
      "ic_norm_per_block": [
        84.81576990374464,
        415.18324375696454,
        118.02203385097607,
        135.80317049869802
      ],
      "ss_norm_per_block": [
        22.82463850820533,
        534.0533630265749,
        75.87437620849218,
        77.28158358697746
      ],
      "abs_diff_per_block": [
        62.14038204348047,
        145.47838763921553,
        62.56157317906481,
        62.40553023708198
      ],
      "rel_diff_per_block": [
        2.7225133060110176,
        0.2724042159659173,
        0.8245415159283069,
        0.8075084300886116
      ],
      "inf_diff_per_block": [
        9.91373612402391,
        10.580304336535306,
        9.949615370525576,
        9.789960072444796
      ]
    },
    {
      "V_RHE": 0.6,
      "method": "cold",
      "z_factor_ss": 1.0,
      "ic_fallback": false,
      "ic_fallback_reason": null,
      "ic_picard_iters": 21,
      "z_at_build": [
        0.0,
        0.0,
        1.0
      ],
      "boltzmann_z_at_build": 1.0,
      "F_norm_total": 3100.2327833293793,
      "F_norms_per_block": [
        3100.227538643231,
        0.26107178949688387,
        5.696600745361677,
        0.007059373449283311
      ],
      "ic_norm_per_block": [
        111.87090624989919,
        426.2412099939719,
        141.22976968522585,
        162.80344218245887
      ],
      "ss_norm_per_block": [
        34.55653291439845,
        522.2789457925466,
        81.87145789576473,
        89.70412852352783
      ],
      "abs_diff_per_block": [
        77.49763705016501,
        132.79412797979882,
        78.14137151658758,
        77.27130564403984
      ],
      "rel_diff_per_block": [
        2.2426334621629405,
        0.2542590105337038,
        0.9544397220344343,
        0.8614018876931949
      ],
      "inf_diff_per_block": [
        12.16178474770641,
        7.343130186501432,
        12.211865464412515,
        11.956371799685241
      ]
    },
    {
      "V_RHE": 0.7,
      "method": "warm<-+23.353",
      "z_factor_ss": 1.0,
      "ic_fallback": false,
      "ic_fallback_reason": null,
      "ic_picard_iters": 21,
      "z_at_build": [
        0.0,
        0.0,
        1.0
      ],
      "boltzmann_z_at_build": 1.0,
      "F_norm_total": 3728.41517902685,
      "F_norms_per_block": [
        3728.4111060593464,
        0.31397139086957604,
        5.5020691503502945,
        0.008256467886973162
      ],
      "ic_norm_per_block": [
        139.3948554555899,
        438.9278909430038,
        166.04571087796307,
        190.24750183005406
      ],
      "ss_norm_per_block": [
        47.89543778800104,
        407.3334717150018,
        90.07388952756426,
        103.53467760757738
      ],
      "abs_diff_per_block": [
        91.80560025654931,
        91.01819626202565,
        92.64702030489842,
        91.30143868938099
      ],
      "rel_diff_per_block": [
        1.9167921726262793,
        0.22344885108216242,
        1.0285668887047088,
        0.8818440429730852
      ],
      "inf_diff_per_block": [
        14.229166271260805,
        14.09732167075316,
        14.2697438465434,
        13.96655743353836
      ]
    },
    {
      "V_RHE": 0.8,
      "method": "warm<-+27.245",
      "z_factor_ss": 1.0,
      "ic_fallback": false,
      "ic_fallback_reason": null,
      "ic_picard_iters": 21,
      "z_at_build": [
        0.0,
        0.0,
        1.0
      ],
      "boltzmann_z_at_build": 1.0,
      "F_norm_total": 3536.5419521612016,
      "F_norms_per_block": [
        3536.539319987272,
        0.29781266834090003,
        4.304508157133799,
        0.009862411635957996
      ],
      "ic_norm_per_block": [
        167.24358410895505,
        453.1063259249864,
        191.90751412098305,
        218.0290023156657
      ],
      "ss_norm_per_block": [
        62.52971594915833,
        408.41167134252754,
        100.21680683889,
        118.62442335197971
      ],
      "abs_diff_per_block": [
        105.27647656934855,
        105.27166428273193,
        106.47955660900976,
        104.57933155415205
      ],
      "rel_diff_per_block": [
        1.683623137756563,
        0.2577587068868129,
        1.062492010748136,
        0.8816003365836951
      ],
      "inf_diff_per_block": [
        16.15641375203463,
        16.155767827869315,
        16.254499493383918,
        15.843933094911257
      ]
    },
    {
      "V_RHE": 0.9,
      "method": "warm<-+31.137",
      "z_factor_ss": 1.0,
      "ic_fallback": false,
      "ic_fallback_reason": null,
      "ic_picard_iters": 21,
      "z_at_build": [
        0.0,
        0.0,
        1.0
      ],
      "boltzmann_z_at_build": 1.0,
      "F_norm_total": 1363.4191619239762,
      "F_norms_per_block": [
        1363.4115990935259,
        0.11480905081309348,
        4.5397445147875946,
        0.009865821618342412
      ],
      "ic_norm_per_block": [
        195.43087112686936,
        468.93522750399626,
        218.6660469319381,
        246.56212851760895
      ],
      "ss_norm_per_block": [
        78.25680047685411,
        414.13233745604373,
        112.26371480248751,
        134.80693435318898
      ],
      "abs_diff_per_block": [
        117.90696940280615,
        117.90719713255707,
        119.35966769310889,
        116.93616387858471
      ],
      "rel_diff_per_block": [
        1.506667391004304,
        0.2847089842267433,
        1.0632078931568025,
        0.8674343381492265
      ],
      "inf_diff_per_block": [
        17.968747414081847,
        17.968777709719703,
        18.086493866118367,
        17.61027896572204
      ]
    },
    {
      "V_RHE": 1.0,
      "method": "warm<-+35.030",
      "z_factor_ss": 1.0,
      "ic_fallback": false,
      "ic_fallback_reason": null,
      "ic_picard_iters": 21,
      "z_at_build": [
        0.0,
        0.0,
        1.0
      ],
      "boltzmann_z_at_build": 1.0,
      "F_norm_total": 3041.115438607482,
      "F_norms_per_block": [
        3041.107952126453,
        0.2560729867967227,
        6.743053894892941,
        0.010041226909946462
      ],
      "ic_norm_per_block": [
        223.96341501862975,
        486.16788153082393,
        246.10104124172506,
        275.36616272855207
      ],
      "ss_norm_per_block": [
        94.92249573166424,
        420.8243535740431,
        125.88922594554371,
        151.93734123506522
      ],
      "abs_diff_per_block": [
        129.95500905880263,
        129.95561182809908,
        131.65059736545857,
        128.80526402662352
      ],
      "rel_diff_per_block": [
        1.3690643936098306,
        0.308812003688455,
        1.0457654050745142,
        0.8477525207404175
      ],
      "inf_diff_per_block": [
        19.684904508072744,
        19.684984160873732,
        19.821472288333936,
        19.283138097495367
      ]
    }
  ]
}