{
  "config": {
    "v_rhe_grid": [
      0.2,
      0.3,
      0.4,
      0.5,
      0.6,
      0.68,
      0.7,
      0.75,
      0.8,
      0.9,
      1.0,
      1.1,
      1.2,
      1.3,
      1.4,
      1.5,
      1.6,
      1.7,
      1.8,
      1.9,
      2.0
    ],
    "mesh_ny": 200,
    "K0_HAT_R1": 0.0012631578947368421,
    "K0_HAT_R2": 5.2631578947368424e-05,
    "ALPHA_R1": 0.627,
    "ALPHA_R2": 0.5,
    "E_EQ_R1": 0.68,
    "E_EQ_R2": 1.78,
    "I_SCALE": 0.18332213250999999,
    "V_T": 0.02569257891379157,
    "formulation": "logc",
    "log_rate": true,
    "counterion_mode": "steric",
    "boltzmann_counterion": {
      "z": -1,
      "c_bulk_nondim": 0.2,
      "phi_clamp": 50.0,
      "steric_mode": "bikerman",
      "a_nondim": 0.01
    },
    "initializer": "debye_boltzmann",
    "exponent_clip": 50.0,
    "stern_capacitance_f_m2": 0.1,
    "wall_seconds": 1360.240031003952
  },
  "rows": [
    {
      "V_RHE": 0.2,
      "cd_mA_cm2": -0.15717375005527373,
      "pc_mA_cm2": 1.5494023232972052e-05,
      "z_factor": 1.0,
      "method": "cold",
      "initializer_fallback": true,
      "initializer_fallback_reason": null,
      "initializer_picard_iters": null
    },
    {
      "V_RHE": 0.3,
      "cd_mA_cm2": -0.11643089926971358,
      "pc_mA_cm2": 1.5481423687892082e-05,
      "z_factor": 1.0,
      "method": "cold",
      "initializer_fallback": true,
      "initializer_fallback_reason": null,
      "initializer_picard_iters": null
    },
    {
      "V_RHE": 0.4,
      "cd_mA_cm2": null,
      "pc_mA_cm2": null,
      "z_factor": 0.0,
      "method": "cold-failed",
      "initializer_fallback": true,
      "initializer_fallback_reason": null,
      "initializer_picard_iters": null
    },
    {
      "V_RHE": 0.5,
      "cd_mA_cm2": -1.560494135112426e-05,
      "pc_mA_cm2": 1.5547746641135612e-05,
      "z_factor": 1.0,
      "method": "cold",
      "initializer_fallback": false,
      "initializer_fallback_reason": null,
      "initializer_picard_iters": null
    },
    {
      "V_RHE": 0.6,
      "cd_mA_cm2": -1.3207130604025816e-05,
      "pc_mA_cm2": 1.320712987880373e-05,
      "z_factor": 1.0,
      "method": "cold",
      "initializer_fallback": false,
      "initializer_fallback_reason": null,
      "initializer_picard_iters": null
    },
    {
      "V_RHE": 0.68,
      "cd_mA_cm2": -4.7713278488340475e-08,
      "pc_mA_cm2": 4.771328156963253e-08,
      "z_factor": 1.0,
      "method": "warm<-+23.353",
      "initializer_fallback": false,
      "initializer_fallback_reason": null,
      "initializer_picard_iters": null
    },
    {
      "V_RHE": 0.7,
      "cd_mA_cm2": -6.917291737529277e-09,
      "pc_mA_cm2": 6.917294589858781e-09,
      "z_factor": 1.0,
      "method": "warm<-+26.467",
      "initializer_fallback": false,
      "initializer_fallback_reason": null,
      "initializer_picard_iters": null
    },
    {
      "V_RHE": 0.75,
      "cd_mA_cm2": -4.809496969391676e-11,
      "pc_mA_cm2": 4.8097088638985184e-11,
      "z_factor": 1.0,
      "method": "warm<-+27.245",
      "initializer_fallback": false,
      "initializer_fallback_reason": null,
      "initializer_picard_iters": null
    },
    {
      "V_RHE": 0.8,
      "cd_mA_cm2": -2.865248462396546e-13,
      "pc_mA_cm2": 2.880143860794225e-13,
      "z_factor": 1.0,
      "method": "warm<-+29.191",
      "initializer_fallback": false,
      "initializer_fallback_reason": null,
      "initializer_picard_iters": null
    },
    {
      "V_RHE": 0.9,
      "cd_mA_cm2": 3.1299112306069623e-16,
      "pc_mA_cm2": 3.266827656394896e-16,
      "z_factor": 1.0,
      "method": "warm<-+31.137",
      "initializer_fallback": false,
      "initializer_fallback_reason": null,
      "initializer_picard_iters": null
    },
    {
      "V_RHE": 1.0,
      "cd_mA_cm2": 1.1686166951837267e-16,
      "pc_mA_cm2": 1.168618748185909e-16,
      "z_factor": 1.0,
      "method": "warm<-+35.030",
      "initializer_fallback": false,
      "initializer_fallback_reason": null,
      "initializer_picard_iters": null
    },
    {
      "V_RHE": 1.1,
      "cd_mA_cm2": 3.7287942793670813e-17,
      "pc_mA_cm2": 3.728794279422977e-17,
      "z_factor": 1.0,
      "method": "warm<-+38.922",
      "initializer_fallback": false,
      "initializer_fallback_reason": null,
      "initializer_picard_iters": null
    },
    {
      "V_RHE": 1.2,
      "cd_mA_cm2": 1.1219285781454053e-17,
      "pc_mA_cm2": 1.1219285781454053e-17,
      "z_factor": 1.0,
      "method": "warm<-+42.814",
      "initializer_fallback": false,
      "initializer_fallback_reason": null,
      "initializer_picard_iters": null
    },
    {
      "V_RHE": 1.3,
      "cd_mA_cm2": 3.2302289680114854e-17,
      "pc_mA_cm2": 3.2302289680114854e-17,
      "z_factor": 1.0,
      "method": "warm<-+46.706",
      "initializer_fallback": false,
      "initializer_fallback_reason": null,
      "initializer_picard_iters": null
    },
    {
      "V_RHE": 1.4,
      "cd_mA_cm2": 9.027971806728219e-17,
      "pc_mA_cm2": 9.027971806728219e-17,
      "z_factor": 1.0,
      "method": "warm<-+50.598",
      "initializer_fallback": false,
      "initializer_fallback_reason": null,
      "initializer_picard_iters": null
    },
    {
      "V_RHE": 1.5,
      "cd_mA_cm2": 9.724921149949619e-17,
      "pc_mA_cm2": 9.724921149949619e-17,
      "z_factor": 1.0,
      "method": "warm<-+54.490",
      "initializer_fallback": false,
      "initializer_fallback_reason": null,
      "initializer_picard_iters": null
    },
    {
      "V_RHE": 1.6,
      "cd_mA_cm2": 4.309003637692575e-16,
      "pc_mA_cm2": 4.309003637692575e-16,
      "z_factor": 1.0,
      "method": "warm<-+58.383",
      "initializer_fallback": false,
      "initializer_fallback_reason": null,
      "initializer_picard_iters": null
    },
    {
      "V_RHE": 1.7,
      "cd_mA_cm2": 2.7790886832295663e-16,
      "pc_mA_cm2": 2.7790886832295663e-16,
      "z_factor": 1.0,
      "method": "warm<-+62.275",
      "initializer_fallback": false,
      "initializer_fallback_reason": null,
      "initializer_picard_iters": null
    },
    {
      "V_RHE": 1.8,
      "cd_mA_cm2": 4.098831046547634e-15,
      "pc_mA_cm2": 4.098831046547634e-15,
      "z_factor": 1.0,
      "method": "warm<-+66.167",
      "initializer_fallback": false,
      "initializer_fallback_reason": null,
      "initializer_picard_iters": null
    },
    {
      "V_RHE": 1.9,
      "cd_mA_cm2": 2.41694751773494e-15,
      "pc_mA_cm2": 2.41694751773494e-15,
      "z_factor": 1.0,
      "method": "warm<-+70.059",
      "initializer_fallback": false,
      "initializer_fallback_reason": null,
      "initializer_picard_iters": null
    },
    {
      "V_RHE": 2.0,
      "cd_mA_cm2": 1.2663245543099333e-15,
      "pc_mA_cm2": 1.2663245543099333e-15,
      "z_factor": 1.0,
      "method": "warm<-+73.951",
      "initializer_fallback": false,
      "initializer_fallback_reason": null,
      "initializer_picard_iters": null
    }
  ],
  "diagnostics": [
    {
      "phase": "cold_z_ramp",
      "max_phi": 5.0971869004061165,
      "min_phi": -2.0300131611407597,
      "max_u0": 0.0,
      "min_u0": -0.8424375126591502,
      "max_u1": -9.210340371976182,
      "min_u1": -17.866345769315895,
      "max_u2": -1.6094379124341003,
      "min_u2": -13.227109955986727,
      "electrode_area_nondim": 1.0,
      "u0_surface_mean": -0.8285362392835152,
      "c0_surface_mean": 0.4366880255039193,
      "u1_surface_mean": -17.85551837151767,
      "c1_surface_mean": 1.7597334917370185e-08,
      "u2_surface_mean": -13.179172794243447,
      "c2_surface_mean": 1.8895482204916961e-06,
      "phi_surface_mean": 5.077344632758784,
      "c_counterion0_surface_mean": 24.435320730206588,
      "c_counterion0_z": -1,
      "c_counterion0_steric_mode": "bikerman",
      "surface_counterion_within_steric": true,
      "picard_iters": 50,
      "initializer_fallback": true,
      "snes_reason": "2",
      "snes_iters": 1
    },
    {
      "phase": "cold_z_ramp",
      "max_phi": 6.71225107058438,
      "min_phi": -1.0476437428685188,
      "max_u0": 0.0,
      "min_u0": -1.3885107420381047,
      "max_u1": -9.210340371976182,
      "min_u1": -21.245999748508538,
      "max_u2": -1.6094379124341003,
      "min_u2": -11.714599424710554,
      "electrode_area_nondim": 1.0,
      "u0_surface_mean": -1.3253717086588537,
      "c0_surface_mean": 0.2657041761878515,
      "u1_surface_mean": -21.228754126923747,
      "c1_surface_mean": 6.032109616376274e-10,
      "u2_surface_mean": -11.642853022336098,
      "c2_surface_mean": 8.781590447707447e-06,
      "phi_surface_mean": 6.675683897788098,
      "c_counterion0_surface_mean": 61.49696427810644,
      "c_counterion0_z": -1,
      "c_counterion0_steric_mode": "bikerman",
      "surface_counterion_within_steric": true,
      "picard_iters": 21,
      "initializer_fallback": true,
      "snes_reason": "2",
      "snes_iters": 0
    },
    {
      "phase": "cold_failed",
      "max_phi": 15.567615891133082,
      "min_phi": 0.0,
      "max_u0": 0.0,
      "min_u0": -0.27691776730340084,
      "max_u1": -9.210340371976182,
      "min_u1": -13.910534672499193,
      "max_u2": -1.6094379124341003,
      "min_u2": -15.442643360970155,
      "electrode_area_nondim": 1.0,
      "u0_surface_mean": -0.27655547835882877,
      "c0_surface_mean": 0.7583915436463508,
      "u1_surface_mean": -13.910167704763992,
      "c1_surface_mean": 9.096847693428011e-07,
      "u2_surface_mean": -15.430264090666483,
      "c2_surface_mean": 1.9893969652833443e-07,
      "phi_surface_mean": 15.567615891133084,
      "c_counterion0_surface_mean": 99.23312387898389,
      "c_counterion0_z": -1,
      "c_counterion0_steric_mode": "bikerman",
      "surface_counterion_within_steric": true,
      "picard_iters": 21,
      "initializer_fallback": true,
      "snes_reason": "-9",
      "snes_iters": 1
    },
    {
      "phase": "cold_z_ramp",
      "max_phi": 9.862171147340767,
      "min_phi": -0.000546904747298313,
      "max_u0": 3.0284363260820092e-05,
      "min_u0": -3.791957561201386,
      "max_u1": -9.210340371976182,
      "min_u1": -23.539501536799662,
      "max_u2": -1.6090624197236436,
      "min_u2": -15.213545185623763,
      "electrode_area_nondim": 1.0,
      "u0_surface_mean": -3.547353592937731,
      "c0_surface_mean": 0.028800757418351756,
      "u1_surface_mean": -23.01680682283638,
      "c1_surface_mean": 1.0090851286151176e-10,
      "u2_surface_mean": -14.861634673005769,
      "c2_surface_mean": 3.512966994356758e-07,
      "phi_surface_mean": 9.764996037675708,
      "c_counterion0_surface_mean": 97.21879096618501,
      "c_counterion0_z": -1,
      "c_counterion0_steric_mode": "bikerman",
      "surface_counterion_within_steric": true,
      "picard_iters": 21,
      "initializer_fallback": false,
      "snes_reason": "2",
      "snes_iters": 0
    },
    {
      "phase": "cold_z_ramp",
      "max_phi": 11.667994257709102,
      "min_phi": -0.0005897848157727967,
      "max_u0": 3.519640857599568e-05,
      "min_u0": -5.600521348419052,
      "max_u1": -9.210340371976182,
      "min_u1": -16.429032592048273,
      "max_u2": -1.6089848860774607,
      "min_u2": -18.801659857736656,
      "electrode_area_nondim": 1.0,
      "u0_surface_mean": -5.263689648951637,
      "c0_surface_mean": 0.005176171187808737,
      "u1_surface_mean": -16.299175313306755,
      "c1_surface_mean": 8.343688882631292e-08,
      "u2_surface_mean": -18.31577230447938,
      "c2_surface_mean": 1.1106089177624439e-08,
      "phi_surface_mean": 11.53029835816928,
      "c_counterion0_surface_mean": 99.51267621881367,
      "c_counterion0_z": -1,
      "c_counterion0_steric_mode": "bikerman",
      "surface_counterion_within_steric": true,
      "picard_iters": 21,
      "initializer_fallback": false,
      "snes_reason": "2",
      "snes_iters": 0
    },
    {
      "phase": "warm_walk_anodic",
      "max_phi": 13.229546846427231,
      "min_phi": -0.0005671536013469991,
      "max_u0": 3.881222137855324e-05,
      "min_u0": -7.171670995057109,
      "max_u1": -9.210340371976182,
      "min_u1": -16.39296355810779,
      "max_u2": -1.6088705854764151,
      "min_u2": -21.899140339900175,
      "electrode_area_nondim": 1.0,
      "u0_surface_mean": -6.764558165774026,
      "c0_surface_mean": 0.001153957239463271,
      "u1_surface_mean": -15.986252484879662,
      "c1_surface_mean": 1.140929368807966e-07,
      "u2_surface_mean": -21.308813360202265,
      "c2_surface_mean": 5.568009168866964e-10,
      "phi_surface_mean": 13.057886659442934,
      "c_counterion0_surface_mean": 99.89379089791899,
      "c_counterion0_z": -1,
      "c_counterion0_steric_mode": "bikerman",
      "surface_counterion_within_steric": true,
      "picard_iters": null,
      "initializer_fallback": false,
      "snes_reason": "2",
      "snes_iters": 0
    },
    {
      "phase": "warm_walk_anodic",
      "max_phi": 13.634323420535729,
      "min_phi": -0.0005783410136360072,
      "max_u0": 3.902602056267844e-05,
      "min_u0": -7.578717660615481,
      "max_u1": -9.210340371976182,
      "min_u1": -16.789987691217906,
      "max_u2": -1.6088589793253394,
      "min_u2": -22.70336350476258,
      "electrode_area_nondim": 1.0,
      "u0_surface_mean": -7.154536552455301,
      "c0_surface_mean": 0.0007813115684089957,
      "u1_surface_mean": -16.36586499120861,
      "c1_surface_mean": 7.805399616679342e-08,
      "u2_surface_mean": -22.087719040945615,
      "c2_surface_mean": 2.555203553049544e-10,
      "phi_surface_mean": 13.454115489526638,
      "c_counterion0_surface_mean": 99.92850748237248,
      "c_counterion0_z": -1,
      "c_counterion0_steric_mode": "bikerman",
      "surface_counterion_within_steric": true,
      "picard_iters": null,
      "initializer_fallback": false,
      "snes_reason": "2",
      "snes_iters": 0
    },
    {
      "phase": "warm_walk_anodic",
      "max_phi": 14.669053587419167,
      "min_phi": -0.0006065023768553438,
      "max_u0": 4.157956504810162e-05,
      "min_u0": -8.618460908225094,
      "max_u1": -9.210340371976182,
      "min_u1": -17.82884456394059,
      "max_u2": -1.6088306969683952,
      "min_u2": -24.758988657656595,
      "electrode_area_nondim": 1.0,
      "u0_surface_mean": -8.152419230075171,
      "c0_surface_mean": 0.00028803768661846005,
      "u1_surface_mean": -17.36280337690007,
      "c1_surface_mean": 2.880250780882737e-08,
      "u2_surface_mean": -24.081586029200203,
      "c2_surface_mean": 3.479365653641194e-11,
      "phi_surface_mean": 14.467490562295135,
      "c_counterion0_surface_mean": 99.97403268134924,
      "c_counterion0_z": -1,
      "c_counterion0_steric_mode": "bikerman",
      "surface_counterion_within_steric": true,
      "picard_iters": null,
      "initializer_fallback": false,
      "snes_reason": "2",
      "snes_iters": 0
    },
    {
      "phase": "warm_walk_anodic",
      "max_phi": 15.733872313904092,
      "min_phi": -0.0006344095770919625,
      "max_u0": 4.3129605256129036e-05,
      "min_u0": -9.687280720412039,
      "max_u1": -9.210298474029853,
      "min_u1": -18.89762232438955,
      "max_u2": -1.6088027850670887,
      "min_u2": -26.873648829801144,
      "electrode_area_nondim": 1.0,
      "u0_surface_mean": -9.180481098625021,
      "c0_surface_mean": 0.00010303095317432499,
      "u1_surface_mean": -18.39082270602734,
      "c1_surface_mean": 1.030308258872713e-08,
      "u2_surface_mean": -26.13635780323042,
      "c2_surface_mean": 4.457835403578833e-12,
      "phi_surface_mean": 15.511078546271222,
      "c_counterion0_surface_mean": 99.99085149317717,
      "c_counterion0_z": -1,
      "c_counterion0_steric_mode": "bikerman",
      "surface_counterion_within_steric": true,
      "picard_iters": null,
      "initializer_fallback": false,
      "snes_reason": "2",
      "snes_iters": 0
    },
    {
      "phase": "warm_walk_anodic",
      "max_phi": 17.94290623983113,
      "min_phi": -0.0006895920857546006,
      "max_u0": 4.623501762921374e-05,
      "min_u0": -11.902301853398962,
      "max_u1": -9.21029366595808,
      "min_u1": -21.112641754381983,
      "max_u2": -1.6087476612588472,
      "min_u2": -31.259986059492256,
      "electrode_area_nondim": 1.0,
      "u0_surface_mean": -11.317421751012825,
      "c0_surface_mean": 1.2159233098011638e-05,
      "u1_surface_mean": -20.52776165178083,
      "c1_surface_mean": 1.2159238827543077e-09,
      "u2_surface_mean": -30.408561179536925,
      "c2_surface_mean": 6.219130601975603e-14,
      "phi_surface_mean": 17.67842557719931,
      "c_counterion0_surface_mean": 99.99895222235891,
      "c_counterion0_z": -1,
      "c_counterion0_steric_mode": "bikerman",
      "surface_counterion_within_steric": true,
      "picard_iters": null,
      "initializer_fallback": false,
      "snes_reason": "2",
      "snes_iters": 0
    },
    {
      "phase": "warm_walk_anodic",
      "max_phi": 20.24347831784763,
      "min_phi": -0.0007434962356904723,
      "max_u0": 4.8806638599736324e-05,
      "min_u0": -14.206223256205803,
      "max_u1": -9.21029109278532,
      "min_u1": -23.41656315565119,
      "max_u2": -1.6086937426852876,
      "min_u2": -35.82600132927013,
      "electrode_area_nondim": 1.0,
      "u0_surface_mean": -13.547300700989114,
      "c0_surface_mean": 1.3076215247209893e-06,
      "u1_surface_mean": -22.75764060021604,
      "c1_surface_mean": 1.3076221428982405e-10,
      "u2_surface_mean": -34.86751675686147,
      "c2_surface_mean": 7.198298877144321e-16,
      "phi_surface_mean": 19.9382928931495,
      "c_counterion0_surface_mean": 99.99989060973773,
      "c_counterion0_z": -1,
      "c_counterion0_steric_mode": "bikerman",
      "surface_counterion_within_steric": true,
      "picard_iters": null,
      "initializer_fallback": false,
      "snes_reason": "2",
      "snes_iters": 0
    },
    {
      "phase": "warm_walk_anodic",
      "max_phi": 22.622705069681427,
      "min_phi": -0.0007961562607523454,
      "max_u0": 5.224858111558828e-05,
      "min_u0": -16.584242656976393,
      "max_u1": -9.210287553381221,
      "min_u1": -25.794582459000093,
      "max_u2": -1.6086409395550088,
      "min_u2": -40.54404838016689,
      "electrode_area_nondim": 1.0,
      "u0_surface_mean": -15.853667331523862,
      "c0_surface_mean": 1.3026860425731964e-07,
      "u1_surface_mean": -25.064007133093998,
      "c1_surface_mean": 1.302686785633404e-11,
      "u2_surface_mean": -39.48306203978028,
      "c2_surface_mean": 7.12400191411311e-18,
      "phi_surface_mean": 22.2777335079657,
      "c_counterion0_surface_mean": 99.99998945254958,
      "c_counterion0_z": -1,
      "c_counterion0_steric_mode": "bikerman",
      "surface_counterion_within_steric": true,
      "picard_iters": null,
      "initializer_fallback": false,
      "snes_reason": "2",
      "snes_iters": 0
    },
    {
      "phase": "warm_walk_anodic",
      "max_phi": 25.069221079300327,
      "min_phi": -0.0008492585988786496,
      "max_u0": 5.493225552471179e-05,
      "min_u0": -18.691502942532992,
      "max_u1": -9.210284857019849,
      "min_u1": -27.90184273218608,
      "max_u2": -1.6085878341492397,
      "min_u2": -45.07066857749642,
      "electrode_area_nondim": 1.0,
      "u0_surface_mean": -18.156657632782192,
      "c0_surface_mean": 1.3021582903549796e-08,
      "u1_surface_mean": -27.36699742180139,
      "c1_surface_mean": 1.3021590494574717e-12,
      "u2_surface_mean": -44.17077297700753,
      "c2_surface_mean": 6.559595128752521e-20,
      "phi_surface_mean": 24.68621744549064,
      "c_counterion0_surface_mean": 99.99999904993639,
      "c_counterion0_z": -1,
      "c_counterion0_steric_mode": "bikerman",
      "surface_counterion_within_steric": true,
      "picard_iters": null,
      "initializer_fallback": false,
      "snes_reason": "2",
      "snes_iters": 0
    },
    {
      "phase": "warm_walk_anodic",
      "max_phi": 27.573785400216632,
      "min_phi": -0.0009022380442466098,
      "max_u0": 5.727005029203243e-05,
      "min_u0": -18.803761663134754,
      "max_u1": -9.210282512053206,
      "min_u1": -28.014101439797482,
      "max_u2": -1.6085348491361189,
      "min_u2": -47.694820388947186,
      "electrode_area_nondim": 1.0,
      "u0_surface_mean": -18.15413683895053,
      "c0_surface_mean": 1.3054449036380258e-08,
      "u1_surface_mean": -27.364476620824227,
      "c1_surface_mean": 1.3054456739845372e-12,
      "u2_surface_mean": -46.64782789674883,
      "c2_surface_mean": 5.509418356318542e-21,
      "phi_surface_mean": 27.15427350785516,
      "c_counterion0_surface_mean": 99.99999990753055,
      "c_counterion0_z": -1,
      "c_counterion0_steric_mode": "bikerman",
      "surface_counterion_within_steric": true,
      "picard_iters": null,
      "initializer_fallback": false,
      "snes_reason": "2",
      "snes_iters": 0
    },
    {
      "phase": "warm_walk_anodic",
      "max_phi": 30.131149922285037,
      "min_phi": -0.0009528053285936948,
      "max_u0": 5.88453595629693e-05,
      "min_u0": -18.834256102689103,
      "max_u1": -9.210280958510845,
      "min_u1": -28.04459590905537,
      "max_u2": -1.6084842685824032,
      "min_u2": -49.31502479725714,
      "electrode_area_nondim": 1.0,
      "u0_surface_mean": -18.14907060873814,
      "c0_surface_mean": 1.3120753696011068e-08,
      "u1_surface_mean": -27.35941042183124,
      "c1_surface_mean": 1.3120761028980394e-12,
      "u2_surface_mean": -48.49523209333463,
      "c2_surface_mean": 8.68536957929003e-22,
      "phi_surface_mean": 29.675357959233896,
      "c_counterion0_surface_mean": 99.99999998049528,
      "c_counterion0_z": -1,
      "c_counterion0_steric_mode": "bikerman",
      "surface_counterion_within_steric": true,
      "picard_iters": null,
      "initializer_fallback": false,
      "snes_reason": "2",
      "snes_iters": 0
    },
    {
      "phase": "warm_walk_anodic",
      "max_phi": 32.73717944587649,
      "min_phi": -0.0010013552571148485,
      "max_u0": 6.036219007263609e-05,
      "min_u0": -19.263801228353504,
      "max_u1": -9.2102794592854,
      "min_u1": -28.47414107704191,
      "max_u2": -1.6084357050018039,
      "min_u2": -49.1596217984032,
      "electrode_area_nondim": 1.0,
      "u0_surface_mean": -19.070466686661728,
      "c0_surface_mean": 5.221575364266371e-09,
      "u1_surface_mean": -28.280806536091447,
      "c1_surface_mean": 5.221578092782826e-13,
      "u2_surface_mean": -48.915472038688996,
      "c2_surface_mean": 5.705325330431069e-22,
      "phi_surface_mean": 32.245408552295146,
      "c_counterion0_surface_mean": 99.99999999428944,
      "c_counterion0_z": -1,
      "c_counterion0_steric_mode": "bikerman",
      "surface_counterion_within_steric": true,
      "picard_iters": null,
      "initializer_fallback": false,
      "snes_reason": "2",
      "snes_iters": 0
    },
    {
      "phase": "warm_walk_anodic",
      "max_phi": 35.38585737747078,
      "min_phi": -0.0010513017673423359,
      "max_u0": 6.263806184418309e-05,
      "min_u0": -19.31802415134805,
      "max_u1": -9.210277197940805,
      "min_u1": -28.52836401461645,
      "max_u2": -1.6083857537548945,
      "min_u2": -48.61657631244943,
      "electrode_area_nondim": 1.0,
      "u0_surface_mean": -18.55941896361691,
      "c0_surface_mean": 8.704558668639703e-09,
      "u1_surface_mean": -27.769758885013967,
      "c1_surface_mean": 8.704562590733017e-13,
      "u2_surface_mean": -47.49785646759117,
      "c2_surface_mean": 2.354740393965318e-21,
      "phi_surface_mean": 34.85994218237897,
      "c_counterion0_surface_mean": 99.99999999125883,
      "c_counterion0_z": -1,
      "c_counterion0_steric_mode": "bikerman",
      "surface_counterion_within_steric": true,
      "picard_iters": null,
      "initializer_fallback": false,
      "snes_reason": "2",
      "snes_iters": 0
    },
    {
      "phase": "warm_walk_anodic",
      "max_phi": 38.07084491529737,
      "min_phi": -0.0011045046296531405,
      "max_u0": 6.543675224789421e-05,
      "min_u0": -20.190593102926933,
      "max_u1": -9.210274415633016,
      "min_u1": -29.400933168759735,
      "max_u2": -1.6083325532044976,
      "min_u2": -49.66900483390082,
      "electrode_area_nondim": 1.0,
      "u0_surface_mean": -19.934691247244537,
      "c0_surface_mean": 2.2002579196603094e-09,
      "u1_surface_mean": -29.14503132163462,
      "c1_surface_mean": 2.2002585744265816e-13,
      "u2_surface_mean": -47.99810589950866,
      "c2_surface_mean": 1.427866044816344e-21,
      "phi_surface_mean": 37.513281383116876,
      "c_counterion0_surface_mean": 99.99999999779702,
      "c_counterion0_z": -1,
      "c_counterion0_steric_mode": "bikerman",
      "surface_counterion_within_steric": true,
      "picard_iters": null,
      "initializer_fallback": false,
      "snes_reason": "2",
      "snes_iters": 0
    },
    {
      "phase": "warm_walk_anodic",
      "max_phi": 40.78850168458787,
      "min_phi": -0.001158715164404891,
      "max_u0": 6.768813960108787e-05,
      "min_u0": -18.80532713744079,
      "max_u1": -9.210272183529852,
      "min_u1": -28.015667516640512,
      "max_u2": -1.6082783405240437,
      "min_u2": -48.87445807192626,
      "electrode_area_nondim": 1.0,
      "u0_surface_mean": -18.09835762665195,
      "c0_surface_mean": 1.3803307126419874e-08,
      "u1_surface_mean": -27.30869830689617,
      "c1_surface_mean": 1.3803302871302151e-12,
      "u2_surface_mean": -45.30402240900133,
      "c2_surface_mean": 2.1120931096474836e-20,
      "phi_surface_mean": 40.20058158519733,
      "c_counterion0_surface_mean": 99.99999998619514,
      "c_counterion0_z": -1,
      "c_counterion0_steric_mode": "bikerman",
      "surface_counterion_within_steric": true,
      "picard_iters": null,
      "initializer_fallback": false,
      "snes_reason": "2",
      "snes_iters": 0
    },
    {
      "phase": "warm_walk_anodic",
      "max_phi": 43.538200502617826,
      "min_phi": -0.0012097251166643607,
      "max_u0": 6.869850802932199e-05,
      "min_u0": -20.292004538888506,
      "max_u1": -9.210271191136346,
      "min_u1": -29.502345874448253,
      "max_u2": -1.6082273158243898,
      "min_u2": -48.79303522934339,
      "electrode_area_nondim": 1.0,
      "u0_surface_mean": -19.546317662796604,
      "c0_surface_mean": 3.2444575592025392e-09,
      "u1_surface_mean": -28.756659537564623,
      "c1_surface_mean": 3.244452683461868e-13,
      "u2_surface_mean": -45.915434182135144,
      "c2_surface_mean": 1.1459886081900131e-20,
      "phi_surface_mean": 42.919442717906065,
      "c_counterion0_surface_mean": 99.99999999675521,
      "c_counterion0_z": -1,
      "c_counterion0_steric_mode": "bikerman",
      "surface_counterion_within_steric": true,
      "picard_iters": null,
      "initializer_fallback": false,
      "snes_reason": "2",
      "snes_iters": 0
    },
    {
      "phase": "warm_walk_anodic",
      "max_phi": 46.32000715788735,
      "min_phi": -0.0012553349333613568,
      "max_u0": 6.884831003141166e-05,
      "min_u0": -21.328705456446635,
      "max_u1": -9.210271054108336,
      "min_u1": -30.539050193907865,
      "max_u2": -1.6081816819653716,
      "min_u2": -51.361144946090704,
      "electrode_area_nondim": 1.0,
      "u0_surface_mean": -21.058554314758737,
      "c0_surface_mean": 7.151317569484938e-10,
      "u1_surface_mean": -30.268898855132853,
      "c1_surface_mean": 7.151287760009689e-14,
      "u2_surface_mean": -46.61433241804012,
      "c2_surface_mean": 5.697084397900644e-21,
      "phi_surface_mean": 45.66930331394899,
      "c_counterion0_surface_mean": 99.9999999992848,
      "c_counterion0_z": -1,
      "c_counterion0_steric_mode": "bikerman",
      "surface_counterion_within_steric": true,
      "picard_iters": null,
      "initializer_fallback": false,
      "snes_reason": "2",
      "snes_iters": 0
    }
  ]
}