{"v_rhe": [-1.003, -0.923833, -0.844667, -0.7655, -0.686333, -0.607167, -0.528, -0.448833, -0.369667, -0.2905, -0.211333, -0.132167, -0.053], "v_rhe_deck": [-0.1, -0.020833, 0.058333, 0.1375, 0.216667, 0.295833, 0.375, 0.454167, 0.533333, 0.6125, 0.691667, 0.770833, 0.85], "cd_mA_cm2": [-3.416959643999248, -3.331365730496557, -3.24067164210471, -3.1265119131170027, -2.5384492875106845, -0.4424917770729681, -0.01848499079075439, -0.0006913984687920697, -2.690192228895137e-05, -1.1008902707907112e-06, -4.742638656021843e-08, -2.127267819550242e-09, -9.641879193612964e-11], "pc_mA_cm2": [-0.6380890751274015, -0.7236506102249399, -0.8134092875897827, -0.9001509818136331, -0.8316524359098942, -0.16357023269769097, -0.007641549308736975, -0.00031671190656193973, -1.3528452583605741e-05, -6.021987693271993e-07, -2.7971387075461226e-08, -1.3418284147639965e-09, -6.4588894297004e-11], "surface_pH": [9.297294083160425, 9.379724998924434, 9.464984107234105, 9.550985323639065, 9.554782606216865, 7.7823809131018935, 2.922955697049288, 3.024603697095946, 3.161328943290906, 3.317341572016731, 3.4922764390492063, 3.682069243583625, 3.875781390048918], "surface_pOH": [4.702705916839574, 4.620275001075566, 4.535015892765894, 4.449014676360935, 4.445217393783135, 6.2176190868981065, 11.077044302950712, 10.975396302904054, 10.838671056709094, 10.682658427983268, 10.507723560950794, 10.317930756416375, 10.124218609951082], "ph_poh_minus_pkw": [0.0, 0.0, 0.0, 0.0, 0.0, 0.0, 0.0, 0.0, 0.0, 0.0, 0.0, 0.0, 0.0], "per_reaction": [[{"label": "R2e_acid", "proton_donor": "hydronium", "n_electrons": 2, "rate_2e_units_mA_cm2": 0.0, "current_mA_cm2": 0.0, "cathodic_mA_cm2": 0.0, "anodic_mA_cm2": 0.0}, {"label": "R2e_water", "proton_donor": "water", "n_electrons": 2, "rate_2e_units_mA_cm2": -0.6380890751274015, "current_mA_cm2": -0.6380890751274015, "cathodic_mA_cm2": -0.6380890751274015, "anodic_mA_cm2": 0.0}, {"label": "R4e_acid", "proton_donor": "hydronium", "n_electrons": 4, "rate_2e_units_mA_cm2": 0.0, "current_mA_cm2": 0.0, "cathodic_mA_cm2": 0.0, "anodic_mA_cm2": 0.0}, {"label": "R4e_water", "proton_donor": "water", "n_electrons": 4, "rate_2e_units_mA_cm2": -1.3894352844359228, "current_mA_cm2": -2.7788705688718456, "cathodic_mA_cm2": -1.3894352844359228, "anodic_mA_cm2": 0.0}], [{"label": "R2e_acid", "proton_donor": "hydronium", "n_electrons": 2, "rate_2e_units_mA_cm2": 0.0, "current_mA_cm2": 0.0, "cathodic_mA_cm2": 0.0, "anodic_mA_cm2": 0.0}, {"label": "R2e_water", "proton_donor": "water", "n_electrons": 2, "rate_2e_units_mA_cm2": -0.7236506102249399, "current_mA_cm2": -0.7236506102249399, "cathodic_mA_cm2": -0.7236506102249399, "anodic_mA_cm2": 0.0}, {"label": "R4e_acid", "proton_donor": "hydronium", "n_electrons": 4, "rate_2e_units_mA_cm2": 0.0, "current_mA_cm2": 0.0, "cathodic_mA_cm2": 0.0, "anodic_mA_cm2": 0.0}, {"label": "R4e_water", "proton_donor": "water", "n_electrons": 4, "rate_2e_units_mA_cm2": -1.3038575601358056, "current_mA_cm2": -2.607715120271611, "cathodic_mA_cm2": -1.3038575601358056, "anodic_mA_cm2": 0.0}], [{"label": "R2e_acid", "proton_donor": "hydronium", "n_electrons": 2, "rate_2e_units_mA_cm2": 0.0, "current_mA_cm2": 0.0, "cathodic_mA_cm2": 0.0, "anodic_mA_cm2": 0.0}, {"label": "R2e_water", "proton_donor": "water", "n_electrons": 2, "rate_2e_units_mA_cm2": -0.8134092875897827, "current_mA_cm2": -0.8134092875897827, "cathodic_mA_cm2": -0.8134092875897827, "anodic_mA_cm2": 0.0}, {"label": "R4e_acid", "proton_donor": "hydronium", "n_electrons": 4, "rate_2e_units_mA_cm2": 0.0, "current_mA_cm2": 0.0, "cathodic_mA_cm2": 0.0, "anodic_mA_cm2": 0.0}, {"label": "R4e_water", "proton_donor": "water", "n_electrons": 4, "rate_2e_units_mA_cm2": -1.2136311772574628, "current_mA_cm2": -2.4272623545149257, "cathodic_mA_cm2": -1.2136311772574628, "anodic_mA_cm2": 0.0}], [{"label": "R2e_acid", "proton_donor": "hydronium", "n_electrons": 2, "rate_2e_units_mA_cm2": 0.0, "current_mA_cm2": 0.0, "cathodic_mA_cm2": 0.0, "anodic_mA_cm2": 0.0}, {"label": "R2e_water", "proton_donor": "water", "n_electrons": 2, "rate_2e_units_mA_cm2": -0.9001509818136331, "current_mA_cm2": -0.9001509818136331, "cathodic_mA_cm2": -0.9001509818136331, "anodic_mA_cm2": 0.0}, {"label": "R4e_acid", "proton_donor": "hydronium", "n_electrons": 4, "rate_2e_units_mA_cm2": 0.0, "current_mA_cm2": 0.0, "cathodic_mA_cm2": 0.0, "anodic_mA_cm2": 0.0}, {"label": "R4e_water", "proton_donor": "water", "n_electrons": 4, "rate_2e_units_mA_cm2": -1.113180465651686, "current_mA_cm2": -2.226360931303372, "cathodic_mA_cm2": -1.113180465651686, "anodic_mA_cm2": 0.0}], [{"label": "R2e_acid", "proton_donor": "hydronium", "n_electrons": 2, "rate_2e_units_mA_cm2": 0.0, "current_mA_cm2": 0.0, "cathodic_mA_cm2": 0.0, "anodic_mA_cm2": 0.0}, {"label": "R2e_water", "proton_donor": "water", "n_electrons": 2, "rate_2e_units_mA_cm2": -0.8316524359098942, "current_mA_cm2": -0.8316524359098942, "cathodic_mA_cm2": -0.8316524359098942, "anodic_mA_cm2": 0.0}, {"label": "R4e_acid", "proton_donor": "hydronium", "n_electrons": 4, "rate_2e_units_mA_cm2": 0.0, "current_mA_cm2": 0.0, "cathodic_mA_cm2": 0.0, "anodic_mA_cm2": 0.0}, {"label": "R4e_water", "proton_donor": "water", "n_electrons": 4, "rate_2e_units_mA_cm2": -0.8533984258003962, "current_mA_cm2": -1.7067968516007923, "cathodic_mA_cm2": -0.8533984258003962, "anodic_mA_cm2": 0.0}], [{"label": "R2e_acid", "proton_donor": "hydronium", "n_electrons": 2, "rate_2e_units_mA_cm2": 0.0, "current_mA_cm2": 0.0, "cathodic_mA_cm2": 0.0, "anodic_mA_cm2": 0.0}, {"label": "R2e_water", "proton_donor": "water", "n_electrons": 2, "rate_2e_units_mA_cm2": -0.16357023269769097, "current_mA_cm2": -0.16357023269769097, "cathodic_mA_cm2": -0.16357023269769097, "anodic_mA_cm2": 0.0}, {"label": "R4e_acid", "proton_donor": "hydronium", "n_electrons": 4, "rate_2e_units_mA_cm2": 0.0, "current_mA_cm2": 0.0, "cathodic_mA_cm2": 0.0, "anodic_mA_cm2": 0.0}, {"label": "R4e_water", "proton_donor": "water", "n_electrons": 4, "rate_2e_units_mA_cm2": -0.1394607721876383, "current_mA_cm2": -0.2789215443752766, "cathodic_mA_cm2": -0.1394607721876383, "anodic_mA_cm2": 0.0}], [{"label": "R2e_acid", "proton_donor": "hydronium", "n_electrons": 2, "rate_2e_units_mA_cm2": 0.0, "current_mA_cm2": 0.0, "cathodic_mA_cm2": 0.0, "anodic_mA_cm2": 0.0}, {"label": "R2e_water", "proton_donor": "water", "n_electrons": 2, "rate_2e_units_mA_cm2": -0.007641549308736975, "current_mA_cm2": -0.007641549308736975, "cathodic_mA_cm2": -0.007641549308736975, "anodic_mA_cm2": 0.0}, {"label": "R4e_acid", "proton_donor": "hydronium", "n_electrons": 4, "rate_2e_units_mA_cm2": 0.0, "current_mA_cm2": 0.0, "cathodic_mA_cm2": 0.0, "anodic_mA_cm2": 0.0}, {"label": "R4e_water", "proton_donor": "water", "n_electrons": 4, "rate_2e_units_mA_cm2": -0.005421720741008706, "current_mA_cm2": -0.010843441482017413, "cathodic_mA_cm2": -0.005421720741008706, "anodic_mA_cm2": 0.0}], [{"label": "R2e_acid", "proton_donor": "hydronium", "n_electrons": 2, "rate_2e_units_mA_cm2": 0.0, "current_mA_cm2": 0.0, "cathodic_mA_cm2": 0.0, "anodic_mA_cm2": 0.0}, {"label": "R2e_water", "proton_donor": "water", "n_electrons": 2, "rate_2e_units_mA_cm2": -0.00031671190656193973, "current_mA_cm2": -0.00031671190656193973, "cathodic_mA_cm2": -0.00031671190656193973, "anodic_mA_cm2": 0.0}, {"label": "R4e_acid", "proton_donor": "hydronium", "n_electrons": 4, "rate_2e_units_mA_cm2": 0.0, "current_mA_cm2": 0.0, "cathodic_mA_cm2": 0.0, "anodic_mA_cm2": 0.0}, {"label": "R4e_water", "proton_donor": "water", "n_electrons": 4, "rate_2e_units_mA_cm2": -0.00018734328111506506, "current_mA_cm2": -0.0003746865622301301, "cathodic_mA_cm2": -0.00018734328111506506, "anodic_mA_cm2": 0.0}], [{"label": "R2e_acid", "proton_donor": "hydronium", "n_electrons": 2, "rate_2e_units_mA_cm2": 0.0, "current_mA_cm2": 0.0, "cathodic_mA_cm2": 0.0, "anodic_mA_cm2": 0.0}, {"label": "R2e_water", "proton_donor": "water", "n_electrons": 2, "rate_2e_units_mA_cm2": -1.3528452583605741e-05, "current_mA_cm2": -1.3528452583605741e-05, "cathodic_mA_cm2": -1.3528452583605741e-05, "anodic_mA_cm2": 0.0}, {"label": "R4e_acid", "proton_donor": "hydronium", "n_electrons": 4, "rate_2e_units_mA_cm2": 0.0, "current_mA_cm2": 0.0, "cathodic_mA_cm2": 0.0, "anodic_mA_cm2": 0.0}, {"label": "R4e_water", "proton_donor": "water", "n_electrons": 4, "rate_2e_units_mA_cm2": -6.686734852672811e-06, "current_mA_cm2": -1.3373469705345621e-05, "cathodic_mA_cm2": -6.686734852672811e-06, "anodic_mA_cm2": 0.0}], [{"label": "R2e_acid", "proton_donor": "hydronium", "n_electrons": 2, "rate_2e_units_mA_cm2": 0.0, "current_mA_cm2": 0.0, "cathodic_mA_cm2": 0.0, "anodic_mA_cm2": 0.0}, {"label": "R2e_water", "proton_donor": "water", "n_electrons": 2, "rate_2e_units_mA_cm2": -6.021987693271993e-07, "current_mA_cm2": -6.021987693271993e-07, "cathodic_mA_cm2": -6.021987693271993e-07, "anodic_mA_cm2": 0.0}, {"label": "R4e_acid", "proton_donor": "hydronium", "n_electrons": 4, "rate_2e_units_mA_cm2": 0.0, "current_mA_cm2": 0.0, "cathodic_mA_cm2": 0.0, "anodic_mA_cm2": 0.0}, {"label": "R4e_water", "proton_donor": "water", "n_electrons": 4, "rate_2e_units_mA_cm2": -2.493457507317562e-07, "current_mA_cm2": -4.986915014635124e-07, "cathodic_mA_cm2": -2.493457507317562e-07, "anodic_mA_cm2": 0.0}], [{"label": "R2e_acid", "proton_donor": "hydronium", "n_electrons": 2, "rate_2e_units_mA_cm2": 0.0, "current_mA_cm2": 0.0, "cathodic_mA_cm2": 0.0, "anodic_mA_cm2": 0.0}, {"label": "R2e_water", "proton_donor": "water", "n_electrons": 2, "rate_2e_units_mA_cm2": -2.7971387075461226e-08, "current_mA_cm2": -2.7971387075461226e-08, "cathodic_mA_cm2": -2.7971387075461226e-08, "anodic_mA_cm2": 0.0}, {"label": "R4e_acid", "proton_donor": "hydronium", "n_electrons": 4, "rate_2e_units_mA_cm2": 0.0, "current_mA_cm2": 0.0, "cathodic_mA_cm2": 0.0, "anodic_mA_cm2": 0.0}, {"label": "R4e_water", "proton_donor": "water", "n_electrons": 4, "rate_2e_units_mA_cm2": -9.727499742378624e-09, "current_mA_cm2": -1.9454999484757248e-08, "cathodic_mA_cm2": -9.727499742378624e-09, "anodic_mA_cm2": 0.0}], [{"label": "R2e_acid", "proton_donor": "hydronium", "n_electrons": 2, "rate_2e_units_mA_cm2": 0.0, "current_mA_cm2": 0.0, "cathodic_mA_cm2": 0.0, "anodic_mA_cm2": 0.0}, {"label": "R2e_water", "proton_donor": "water", "n_electrons": 2, "rate_2e_units_mA_cm2": -1.3418284147639965e-09, "current_mA_cm2": -1.3418284147639965e-09, "cathodic_mA_cm2": -1.3418284147639965e-09, "anodic_mA_cm2": 0.0}, {"label": "R4e_acid", "proton_donor": "hydronium", "n_electrons": 4, "rate_2e_units_mA_cm2": 0.0, "current_mA_cm2": 0.0, "cathodic_mA_cm2": 0.0, "anodic_mA_cm2": 0.0}, {"label": "R4e_water", "proton_donor": "water", "n_electrons": 4, "rate_2e_units_mA_cm2": -3.92719702393122e-10, "current_mA_cm2": -7.85439404786244e-10, "cathodic_mA_cm2": -3.92719702393122e-10, "anodic_mA_cm2": 0.0}], [{"label": "R2e_acid", "proton_donor": "hydronium", "n_electrons": 2, "rate_2e_units_mA_cm2": 0.0, "current_mA_cm2": 0.0, "cathodic_mA_cm2": 0.0, "anodic_mA_cm2": 0.0}, {"label": "R2e_water", "proton_donor": "water", "n_electrons": 2, "rate_2e_units_mA_cm2": -6.4588894297004e-11, "current_mA_cm2": -6.4588894297004e-11, "cathodic_mA_cm2": -6.4588894297004e-11, "anodic_mA_cm2": 0.0}, {"label": "R4e_acid", "proton_donor": "hydronium", "n_electrons": 4, "rate_2e_units_mA_cm2": 0.0, "current_mA_cm2": 0.0, "cathodic_mA_cm2": 0.0, "anodic_mA_cm2": 0.0}, {"label": "R4e_water", "proton_donor": "water", "n_electrons": 4, "rate_2e_units_mA_cm2": -1.591494881956287e-11, "current_mA_cm2": -3.182989763912574e-11, "cathodic_mA_cm2": -1.591494881956287e-11, "anodic_mA_cm2": 0.0}]], "ledger": [{"electron_consistency_residual_mA_cm2": -8.881784197001252e-16, "e_sink_acid_mA_cm2": 0.0, "e_sink_water_mA_cm2": -3.416959643999247, "o2_consumption_2e_units_mA_cm2": -2.0275243595633246, "anodic_share_2e": 0.0}, {"electron_consistency_residual_mA_cm2": -5.773159728050814e-15, "e_sink_acid_mA_cm2": 0.0, "e_sink_water_mA_cm2": -3.331365730496551, "o2_consumption_2e_units_mA_cm2": -2.0275081703607456, "anodic_share_2e": 0.0}, {"electron_consistency_residual_mA_cm2": -1.7763568394002505e-15, "e_sink_acid_mA_cm2": 0.0, "e_sink_water_mA_cm2": -3.2406716421047084, "o2_consumption_2e_units_mA_cm2": -2.0270404648472455, "anodic_share_2e": 0.0}, {"electron_consistency_residual_mA_cm2": 2.220446049250313e-15, "e_sink_acid_mA_cm2": 0.0, "e_sink_water_mA_cm2": -3.126511913117005, "o2_consumption_2e_units_mA_cm2": -2.013331447465319, "anodic_share_2e": 0.0}, {"electron_consistency_residual_mA_cm2": 1.7763568394002505e-15, "e_sink_acid_mA_cm2": 0.0, "e_sink_water_mA_cm2": -2.5384492875106863, "o2_consumption_2e_units_mA_cm2": -1.6850508617102904, "anodic_share_2e": 0.0}, {"electron_consistency_residual_mA_cm2": -4.996003610813204e-16, "e_sink_acid_mA_cm2": 0.0, "e_sink_water_mA_cm2": -0.4424917770729676, "o2_consumption_2e_units_mA_cm2": -0.3030310048853293, "anodic_share_2e": 0.0}, {"electron_consistency_residual_mA_cm2": 0.0, "e_sink_acid_mA_cm2": 0.0, "e_sink_water_mA_cm2": -0.01848499079075439, "o2_consumption_2e_units_mA_cm2": -0.013063270049745682, "anodic_share_2e": 0.0}, {"electron_consistency_residual_mA_cm2": 1.0842021724855044e-19, "e_sink_acid_mA_cm2": 0.0, "e_sink_water_mA_cm2": -0.0006913984687920698, "o2_consumption_2e_units_mA_cm2": -0.0005040551876770048, "anodic_share_2e": 0.0}, {"electron_consistency_residual_mA_cm2": -6.776263578034403e-21, "e_sink_acid_mA_cm2": 0.0, "e_sink_water_mA_cm2": -2.6901922288951362e-05, "o2_consumption_2e_units_mA_cm2": -2.021518743627855e-05, "anodic_share_2e": 0.0}, {"electron_consistency_residual_mA_cm2": 4.235164736271502e-22, "e_sink_acid_mA_cm2": 0.0, "e_sink_water_mA_cm2": -1.1008902707907116e-06, "o2_consumption_2e_units_mA_cm2": -8.515445200589556e-07, "anodic_share_2e": 0.0}, {"electron_consistency_residual_mA_cm2": 4.632211430296955e-23, "e_sink_acid_mA_cm2": 0.0, "e_sink_water_mA_cm2": -4.7426386560218474e-08, "o2_consumption_2e_units_mA_cm2": -3.7698886817839847e-08, "anodic_share_2e": 0.0}, {"electron_consistency_residual_mA_cm2": -1.6543612251060553e-24, "e_sink_acid_mA_cm2": 0.0, "e_sink_water_mA_cm2": -2.1272678195502404e-09, "o2_consumption_2e_units_mA_cm2": -1.7345481171571184e-09, "anodic_share_2e": 0.0}, {"electron_consistency_residual_mA_cm2": 9.04728794979874e-26, "e_sink_acid_mA_cm2": 0.0, "e_sink_water_mA_cm2": -9.641879193612973e-11, "o2_consumption_2e_units_mA_cm2": -8.050384311656687e-11, "anodic_share_2e": 0.0}], "converged": [true, true, true, true, true, true, true, true, true, true, true, true, true], "n_converged": 13, "n_total": 13, "anchor_converged": true, "anchor_wall_seconds": 2.997138023376465, "anchor_ladder_history": [[1e-12, "ok"], [1e-09, "ok"], [1e-06, "ok"], [0.001, "ok"], [1.0, "ok"]], "grid_wall_seconds": 495.90586495399475, "config": {"driver": "solver_demo_slide15_dual_pathway_cs", "routes": "water", "k0_water_2e_factor": 0.09801674336236157, "k0_water_4e_factor": 4.909906447302814e-13, "k0_acid_4e_factor": 1e-15, "alpha_water_2e": 0.5770144526758703, "alpha_water_4e": 0.304853786169721, "l_eff_um": 21.7, "bulk_h_mol_m3": 0.1, "enable_water_ionization": true, "coarse_grid": true, "cation": "k", "ocp_shift": {"V_OCP_RHE": 0.903, "applied_to": ["V_RHE", "all reaction E_eq_v"]}, "proton_frame": {"frame": "she", "bulk_h_anchor_mol_m3": 0.000407, "ph_anchor": 6.39040559077478, "nernst_slope_v_per_ph": 0.059159349207469625, "she_eeq_shift_v": -0.14141483909213293}, "anchor": {"v_rhe_solver": 0.0, "initializer": "linear_phi", "kw_eff_ladder": null, "max_inserts_per_step": 6}, "stern": {"anchor_f_m2": 0.1, "final_f_m2": 0.2}, "mesh": {"Nx": 8, "Ny": 80, "beta": 3.0}, "exponent_clip": 100.0, "u_clamp": 100.0, "formulation": "logc_muh", "reactions": [{"k0": 0.0, "alpha": 0.627, "cathodic_species": 0, "anodic_species": 1, "c_ref": 1.0, "stoichiometry": [-1, 1, -2], "n_electrons": 2, "reversible": true, "E_eq_v": -0.349414839092133, "cathodic_conc_factors": [{"species": 2, "power": 2, "c_ref_nondim": 0.08333333333333334}], "label": "R2e_acid", "proton_donor": "hydronium", "produces_h2o2": true}, {"k0": 0.000123810623194562, "alpha": 0.5770144526758703, "cathodic_species": 0, "anodic_species": null, "c_ref": 0.0, "stoichiometry": [-1, 1, -2], "n_electrons": 2, "reversible": false, "E_eq_v": -0.349414839092133, "cathodic_conc_factors": [], "label": "R2e_water", "proton_donor": "water", "produces_h2o2": true}, {"k0": 0.0, "alpha": 0.5, "cathodic_species": 0, "anodic_species": null, "c_ref": 0.0, "stoichiometry": [-1, 0, -4], "n_electrons": 4, "reversible": false, "E_eq_v": 0.18558516090786714, "cathodic_conc_factors": [{"species": 2, "power": 4, "c_ref_nondim": 0.08333333333333334}], "label": "R4e_acid", "proton_donor": "hydronium"}, {"k0": 6.201987091329871e-16, "alpha": 0.304853786169721, "cathodic_species": 0, "anodic_species": null, "c_ref": 0.0, "stoichiometry": [-1, 0, -4], "n_electrons": 4, "reversible": false, "E_eq_v": 0.18558516090786714, "cathodic_conc_factors": [], "label": "R4e_water", "proton_donor": "water"}], "v_grid_n": 13}}